LICENSE
README.md
setup.cfg
setup.py
graphene_disable_introspection/__init__.py
graphene_disable_introspection/__version__.py
graphene_disable_introspection/conf.py
graphene_disable_introspection/middleware.py
graphene_disable_introspection/validators.py
graphene_disable_introspection.egg-info/PKG-INFO
graphene_disable_introspection.egg-info/SOURCES.txt
graphene_disable_introspection.egg-info/dependency_links.txt
graphene_disable_introspection.egg-info/top_level.txt