Metadata-Version: 2.1
Name: graphene-disable-introspection
Version: 0.2
Summary: Middleware for Python Graphene to disable introspection
Home-page: https://github.com/Paprikaschote/graphene-disable-introspection
Download-URL: https://github.com/Paprikaschote/graphene-disable-introspection/archive/refs/tags/v0.2.tar.gz
Author: Carlo Völker
Author-email: carlovoelker@gmx.net
License: GPL-3.0
Keywords: django,graphene,graphql,introspection,middleware,__schema,disable,security
Classifier: Development Status :: 5 - Production/Stable
Classifier: Intended Audience :: Developers
Classifier: Topic :: Software Development :: Libraries :: Python Modules
Classifier: License :: OSI Approved :: GNU General Public License v3 (GPLv3)
Classifier: Programming Language :: Python :: 3
Classifier: Programming Language :: Python :: 3.8
Classifier: Programming Language :: Python :: 3.9
Classifier: Programming Language :: Python :: 3.10
Classifier: Programming Language :: Python :: 3.11
Classifier: Framework :: Django
Requires-Python: >=3.8
License-File: LICENSE
